glide_sync/config.py
glide_sync/__init__.py
glide_sync/glide_client.py
glide_sync/logger.py
glide_sync/py.typed
glide_sync/_glide_ffi.py
glide_sync/libglide_ffi.dylib
glide_sync/sync_commands/glide_json.py
glide_sync/sync_commands/ft.py
glide_sync/sync_commands/__init__.py
glide_sync/sync_commands/core.py
glide_sync/sync_commands/standalone_commands.py
glide_sync/sync_commands/cluster_commands.py
glide_sync/sync_commands/cluster_scan_cursor.py
glide_sync/sync_commands/script.py
glide_shared/config.py
glide_shared/protobuf_codec.py
glide_shared/constants.py
glide_shared/__init__.py
glide_shared/py.typed
glide_shared/exceptions.py
glide_shared/routes.py
glide_shared/commands/sorted_set.py
glide_shared/commands/batch.py
glide_shared/commands/__init__.py
glide_shared/commands/core_options.py
glide_shared/commands/stream.py
glide_shared/commands/batch_options.py
glide_shared/commands/command_args.py
glide_shared/commands/bitmap.py
glide_shared/commands/server_modules/json_batch.py
glide_shared/commands/server_modules/json_options.py
glide_shared/commands/server_modules/ft_options/ft_search_options.py
glide_shared/commands/server_modules/ft_options/ft_aggregate_options.py
glide_shared/commands/server_modules/ft_options/ft_create_options.py
glide_shared/commands/server_modules/ft_options/ft_profile_options.py
glide_shared/commands/server_modules/ft_options/ft_constants.py
glide_shared/protobuf/response_pb2.pyi
glide_shared/protobuf/connection_request_pb2.pyi
glide_shared/protobuf/command_request_pb2.py
glide_shared/protobuf/connection_request_pb2.py
glide_shared/protobuf/command_request_pb2.pyi
glide_shared/protobuf/response_pb2.py
valkey_glide_sync-2.2.6.dist-info/RECORD
valkey_glide_sync-2.2.6.dist-info/WHEEL
valkey_glide_sync-2.2.6.dist-info/top_level.txt
valkey_glide_sync-2.2.6.dist-info/METADATA
