Metadata-Version: 2.4
Name: valkey-glide-sync
Version: 2.2.6
Summary: Valkey GLIDE Sync client. Supports Valkey and Redis OSS.
License: Apache-2.0
Classifier: Topic :: Database
Classifier: Topic :: Utilities
Classifier: Intended Audience :: Developers
Classifier: Topic :: Software Development
Classifier: Programming Language :: Rust
Classifier: Programming Language :: Python :: Implementation :: CPython
Classifier: Programming Language :: Python :: Implementation :: PyPy
Requires-Dist: cffi>=1.0.0
Requires-Dist: typing-extensions>=4.8.0
Requires-Dist: protobuf>=3.20
